puzzle_rs-0.2.0.dist-info/METADATA
puzzle_rs-0.2.0.dist-info/WHEEL
puzzle_rs.libs/libgcc_s-e52197c3.so.1
puzzle_rs/__init__.py
puzzle_rs/puzzle_rs.cpython-312-aarch64-linux-musl.so
puzzle_rs-0.2.0.dist-info/RECORD
